mazel/__init__.py
mazel/base.py
mazel/commands/__init__.py
mazel/commands/clean.py
mazel/commands/contrib.py
mazel/commands/echo.py
mazel/commands/format.py
mazel/commands/info.py
mazel/commands/label_common.py
mazel/commands/run.py
mazel/commands/test.py
mazel/commands/utils.py
mazel/contrib/__init__.py
mazel/contrib/dependabot.py
mazel/contrib/link_readme.py
mazel/exceptions.py
mazel/fs.py
mazel/git.py
mazel/graph.py
mazel/info.py
mazel/label.py
mazel/main.py
mazel/package.py
mazel/py.typed
mazel/roles.py
mazel/runtimes/__init__.py
mazel/runtimes/base.py
mazel/runtimes/docker.py
mazel/runtimes/go.py
mazel/runtimes/javascript.py
mazel/runtimes/meteor.py
mazel/runtimes/python.py
mazel/types.py
mazel/workspace.py
mazel-0.0.5.dist-info/LICENSE
mazel-0.0.5.dist-info/METADATA
mazel-0.0.5.dist-info/WHEEL
mazel-0.0.5.dist-info/entry_points.txt
mazel-0.0.5.dist-info/RECORD
