Metadata-Version: 2.1
Name: mazel
Version: 0.0.5
Summary: Simple bazel-inspired Makefile runner for monorepos
Home-page: https://github.com/equium-io/mazel
License: Apache-2.0
Author: John Paulett
Author-email: john.paulett@equium.io
Requires-Python: >=3.10,<4.0
Classifier: License :: OSI Approved :: Apache Software License
Classifier: Programming Language :: Python :: 3
Classifier: Programming Language :: Python :: 3.10
Classifier: Programming Language :: Python :: 3.11
Classifier: Programming Language :: Python :: 3.12
Provides-Extra: yaml
Requires-Dist: click (>=8.1.3,<9.0.0)
Requires-Dist: ruamel.yaml (>=0.17.21,<0.18.0) ; extra == "yaml"
Requires-Dist: tomlkit (>=0.11.5,<0.12.0)
Project-URL: Repository, https://github.com/equium-io/mazel
